{"1":{"id":1,"sha":"9117d2ff932a5203428c6662c13536a23f0c3f11","date":"23 Dec 2020 (17:23:43)","timestamp":20201223172343,"message":"翻譯完成!\n\nDEV - 2","author":"xMikux","avatar":"https://avatars0.githubusercontent.com/u/26039249?v=4","license":{"name":"MIT License","id":"MIT","url":"https://raw.githubusercontent.com/xMikux/DynaTech/master/LICENSE"},"candidate":"DEVELOPMENT","status":"SUCCESS"},"2":{"id":2,"sha":"d82d4eb0240e8002aca9f684e979cfdfe6ed8cd7","date":"24 Dec 2020 (06:31:07)","timestamp":20201224063107,"message":"Merge remote-tracking branch 'ProfElements/master'\n\nDEV - 3","author":"xMikux","avatar":"https://avatars0.githubusercontent.com/u/26039249?v=4","license":{"name":"MIT License","id":"MIT","url":"https://raw.githubusercontent.com/xMikux/DynaTech/master/LICENSE"},"candidate":"DEVELOPMENT","status":"SUCCESS"},"3":{"id":3,"sha":"38aa60258cfd0ad006c5908fe0953872632b6986","date":"27 Dec 2020 (06:13:37)","timestamp":20201227061337,"message":"Merge remote-tracking branch 'ProfElements/master'\n\nDEV - 6","author":"xMikux","avatar":"https://avatars0.githubusercontent.com/u/26039249?v=4","license":{"name":"MIT License","id":"MIT","url":"https://raw.githubusercontent.com/xMikux/DynaTech/master/LICENSE"},"candidate":"DEVELOPMENT","status":"SUCCESS"},"last_successful":3,"latest":3}